notion/__init__.py
notion/core.py
notion/database.py
notion/exceptions.py
notion/notion.py
notion/page.py
notion/user.py
easy_notion_api-0.1.5.dist-info/LICENSE
easy_notion_api-0.1.5.dist-info/METADATA
easy_notion_api-0.1.5.dist-info/WHEEL
easy_notion_api-0.1.5.dist-info/top_level.txt
easy_notion_api-0.1.5.dist-info/RECORD
