Metadata-Version: 2.1
Name: easy-notion-api
Version: 0.1.5
Summary: Unofficial Python API client for Notion
Home-page: https://github.com/Hans97a/easy-notion-api
Author: Hans97a
Author-email: byby8992@naver.com
Classifier: Programming Language :: Python :: 3
Classifier: License :: OSI Approved :: MIT License
Classifier: Operating System :: OS Independent
Requires-Python: >=3.11
License-File: LICENSE
Requires-Dist: certifi ==2024.2.2 ; python_version >= "3.11" and python_version < "4.0"
Requires-Dist: charset-normalizer ==3.3.2 ; python_version >= "3.11" and python_version < "4.0"
Requires-Dist: idna ==3.6 ; python_version >= "3.11" and python_version < "4.0"
Requires-Dist: requests ==2.31.0 ; python_version >= "3.11" and python_version < "4.0"
Requires-Dist: urllib3 ==2.2.1 ; python_version >= "3.11" and python_version < "4.0"
